{
  "$schema": "https://zed.dev/schema/themes/v0.2.0.json",
  "name": "Zedrizon | Horizon",
  "author": "0xnoid",
  "themes": [
    {
      "name": "Zedrizon | Horizon",
      "appearance": "dark",
      "style": {
        "background": "#1C1E26",
        "elevated_surface.background": "#232530",
        "surface.background": "#1C1E26",

        "accents": ["#E95378"],

        "text": "#D5D8DA",
        "text.muted": "#D5D8DA80",
        "text.placeholder": "#D5D8DA4D",
        "text.disabled": "#D5D8DA4D",
        "text.accent": "#E95378",

        "icon": "#D5D8DAB3",
        "icon.muted": "#D5D8DA80",
        "icon.disabled": "#D5D8DA4D",
        "icon.placeholder": "#D5D8DA4D",
        "icon.accent": "#E95378",

        "border": "#1A1C23",
        "border.variant": "#232530",
        "border.focused": "#E9436D",
        "border.selected": "#E95378",
        "border.transparent": "#00000000",
        "border.disabled": "#1A1C23",

        "element.background": "#00000000",
        "element.hover": "#2E303E80",
        "element.active": "#2E303EB3",
        "element.selected": "#2E303E80",
        "element.disabled": "#00000000",
        "error": "#F43E5C",
        "error.background": "#F43E5C1A",
        "warning": "#27D797",
        "warning.background": "#27D7971A",
        "success": "#09F7A0",
        "success.background": "#09F7A01A",
        "info": "#26BBD9",
        "info.background": "#2E303E",

        "ghost_element.background": "#00000000",
        "ghost_element.hover": "#2E303E80",
        "ghost_element.active": "#2E303EB3",
        "ghost_element.selected": "#2E303E80",
        "ghost_element.disabled": "#00000000",

        "drop_target.background": "#2E303E80",

        "status_bar.background": "#1C1E26",
        "title_bar.background": "#1C1E26",
        "title_bar.inactive_background": "#1C1E26",
        "toolbar.background": "#1C1E26",
        "tab_bar.background": "#1C1E26",
        "tab.inactive_background": "#1C1E26",
        "tab.active_background": "#1C1E26",
        "panel.background": "#1C1E26",
        "pane.focused_border": "#E9436D",

        "scrollbar.thumb.background": "#6C6F931A",
        "scrollbar.thumb.hover_background": "#6C6F934D",
        "scrollbar.thumb.border": "#00000000",
        "scrollbar.track.background": "#00000000",
        "scrollbar.track.border": "#1A1C23",

        "editor.foreground": "#D5D8DA",
        "editor.background": "#1C1E26",
        "editor.gutter.background": "#1C1E26",
        "editor.subheader.background": "#232530",
        "editor.active_line.background": "#2E303E4D",
        "editor.highlighted_line.background": "#2E303E4D",
        "editor.line_number": "#D5D8DA1A",
        "editor.active_line_number": "#D5D8DA80",
        "editor.invisible": "#D5D8DA1A",
        "editor.wrap_guide": "#6C6F934D",
        "editor.active_wrap_guide": "#6C6F934D",
        "editor.indent_guide": "#2E303E80",
        "editor.indent_guide_active": "#2E303E",
        "editor.document_highlight.read_background": "#6C6F9380",
        "editor.document_highlight.write_background": "#6C6F9380",

        "terminal.background": "#1C1E26",
        "terminal.foreground": "#D5D8DA",
        "terminal.bright_foreground": "#FFFFFF",
        "terminal.dim_foreground": "#D5D8DA80",
        "terminal.ansi.black": "#16161C",
        "terminal.ansi.bright_black": "#232530",
        "terminal.ansi.red": "#E95678",
        "terminal.ansi.bright_red": "#EC6A88",
        "terminal.ansi.green": "#29D398",
        "terminal.ansi.bright_green": "#3FDAA4",
        "terminal.ansi.yellow": "#FAB795",
        "terminal.ansi.bright_yellow": "#FBC3A7",
        "terminal.ansi.blue": "#26BBD9",
        "terminal.ansi.bright_blue": "#3FC4DE",
        "terminal.ansi.magenta": "#EE64AC",
        "terminal.ansi.bright_magenta": "#F075B5",
        "terminal.ansi.cyan": "#59E1E3",
        "terminal.ansi.bright_cyan": "#6BE4E6",
        "terminal.ansi.white": "#D5D8DA",
        "terminal.ansi.bright_white": "#FFFFFF",

        "link_text.hover": "#E95378",
        "search.match_background": "#6C6F9380",

        "conflict": "#FAB795E6",
        "created": "#09F7A0B3",
        "deleted": "#F43E5CB3",
        "modified": "#FAB38EE6",
        "hidden": "#D5D8DA4D",
        "ignored": "#D5D8DA4D",
        "renamed": "#25B0BCE6",

        "players": [
          {
            "cursor": "#E95378",
            "background": "#E95378",
            "selection": "#2E303EB3"
          },
          {
            "cursor": "#25B0BC",
            "background": "#25B0BC",
            "selection": "#25B0BC40"
          },
          {
            "cursor": "#B877DB",
            "background": "#B877DB",
            "selection": "#B877DB40"
          },
          {
            "cursor": "#FAB795",
            "background": "#FAB795",
            "selection": "#FAB79540"
          },
          {
            "cursor": "#09F7A0",
            "background": "#09F7A0",
            "selection": "#09F7A040"
          },
          {
            "cursor": "#26BBD9",
            "background": "#26BBD9",
            "selection": "#26BBD940"
          },
          {
            "cursor": "#EE64AC",
            "background": "#EE64AC",
            "selection": "#EE64AC40"
          },
          {
            "cursor": "#FAC29A",
            "background": "#FAC29A",
            "selection": "#FAC29A40"
          }
        ],

        "syntax": {
          "attribute": { "color": "#F09483E6" },
          "boolean": { "color": "#F09483E6" },
          "comment": { "color": "#BBBBBB4D", "font_style": "italic" },
          "comment.doc": { "color": "#BBBBBB80", "font_style": "italic" },
          "constant": { "color": "#F09483E6" },
          "constructor": { "color": "#FAC29AE6" },
          "embedded": { "color": "#B877DBE6" },
          "emphasis": { "color": "#25B0BCE6", "font_style": "italic" },
          "emphasis.strong": { "color": "#B877DBE6", "font_weight": 700 },
          "enum": { "color": "#FAC29AE6" },
          "function": { "color": "#25B0BCE6" },
          "function.builtin": { "color": "#25B0BCE6" },
          "function.call": { "color": "#25B0BCE6" },
          "function.definition": { "color": "#25B0BCE6" },
          "function.method": { "color": "#25B0BCE6" },
          "function.method.builtin": { "color": "#25B0BCE6" },
          "hint": { "color": "#6C6F93" },
          "keyword": { "color": "#B877DBE6" },
          "label": { "color": "#FAC29AE6" },
          "link_text": { "color": "#FAB795E6" },
          "link_uri": { "color": "#25B0BCE6" },
          "number": { "color": "#F09483E6" },
          "operator": { "color": "#BBBBBB" },
          "predictive": { "color": "#6C6F934D" },
          "preproc": { "color": "#B877DBE6" },
          "primary": { "color": "#D5D8DA" },
          "property": { "color": "#E95678E6" },
          "punctuation": { "color": "#BBBBBB" },
          "punctuation.bracket": { "color": "#E95678B3" },
          "punctuation.delimiter": { "color": "#BBBBBB" },
          "punctuation.list_marker": { "color": "#F09483E6" },
          "punctuation.special": { "color": "#B877DBE6" },
          "string": { "color": "#FAB795E6" },
          "string.escape": { "color": "#25B0BCE6" },
          "string.regex": { "color": "#F09483E6" },
          "string.special": { "color": "#F09483E6" },
          "string.special.symbol": { "color": "#FAB795E6" },
          "tag": { "color": "#E95678E6" },
          "text.literal": { "color": "#F09483E6" },
          "title": { "color": "#E95678E6" },
          "type": { "color": "#FAC29AE6" },
          "type.builtin": { "color": "#FAC29AE6" },
          "variable": { "color": "#E95678E6" },
          "variable.builtin": { "color": "#FAC29AE6", "font_style": "italic" },
          "variable.member": { "color": "#E95678E6" },
          "variable.parameter": {
            "color": "#E95678E6",
            "font_style": "italic"
          },
          "variant": { "color": "#FAC29AE6" }
        }
      }
    },
    {
      "name": "Zedrizon | Horizon Blur",
      "appearance": "dark",
      "style": {
        "background.appearance": "blurred",

        "background": "#1C1E26D7",
        "elevated_surface.background": "#232530",
        "surface.background": "#1C1E26D0",

        "accents": ["#E95378"],

        "text": "#D5D8DA",
        "text.muted": "#D5D8DA80",
        "text.placeholder": "#D5D8DA4D",
        "text.disabled": "#D5D8DA4D",
        "text.accent": "#E95378",

        "icon": "#D5D8DAB3",
        "icon.muted": "#D5D8DA80",
        "icon.disabled": "#D5D8DA4D",
        "icon.placeholder": "#D5D8DA4D",
        "icon.accent": "#E95378",

        "border": "#2E303E15",
        "border.variant": "#00000000",
        "border.focused": "#E9436D",
        "border.selected": "#E95378",
        "border.transparent": "#00000000",
        "border.disabled": "#2E303E15",

        "element.background": "#00000000",
        "element.hover": "#2E303E80",
        "element.active": "#2E303EB3",
        "element.selected": "#2E303E80",
        "element.disabled": "#00000000",
        "error": "#F43E5C",
        "error.background": "#F43E5C1A",
        "warning": "#27D797",
        "warning.background": "#27D7971A",
        "success": "#09F7A0",
        "success.background": "#09F7A01A",
        "info": "#26BBD9",
        "info.background": "#2E303E",

        "ghost_element.background": "#1C1E2660",
        "ghost_element.hover": "#2E303E90",
        "ghost_element.active": "#2E303EB3",
        "ghost_element.selected": "#2E303E80",
        "ghost_element.disabled": "#00000000",

        "drop_target.background": "#2E303E80",

        "status_bar.background": "#1C1E26D7",
        "title_bar.background": "#1C1E26D7",
        "title_bar.inactive_background": "#171820",
        "toolbar.background": "#00000000",
        "tab_bar.background": "#00000000",
        "tab.inactive_background": "#00000000",
        "tab.active_background": "#232530B0",
        "panel.background": "#00000000",
        "panel.focused_border": "#00000000",
        "panel.overlay_background": "#1C1E26",
        "panel.indent_guide": "#2E303E99",
        "panel.indent_guide_active": "#6C6F93",
        "panel.indent_guide_hover": "#E95378",
        "pane.focused_border": "#E9436D",
        "pane_group.border": "#2E303E15",

        "scrollbar.thumb.background": "#6C6F931A",
        "scrollbar.thumb.hover_background": "#6C6F934D",
        "scrollbar.thumb.active_background": null,
        "scrollbar.thumb.border": null,
        "scrollbar.track.background": "#00000000",
        "scrollbar.track.border": "#00000000",

        "minimap.thumb.background": "#E9537833",
        "minimap.thumb.hover_background": "#E9537866",
        "minimap.thumb.active_background": "#E9537899",
        "minimap.thumb.border": null,

        "editor.foreground": "#D5D8DA",
        "editor.background": "#00000000",
        "editor.gutter.background": "#00000000",
        "editor.subheader.background": "#232530",
        "editor.active_line.background": "#00000000",
        "editor.highlighted_line.background": "#2E303E26",
        "editor.line_number": "#D5D8DA1A",
        "editor.active_line_number": "#D5D8DA80",
        "editor.invisible": "#D5D8DA1A",
        "editor.wrap_guide": "#6C6F934D",
        "editor.active_wrap_guide": "#6C6F934D",
        "editor.indent_guide": "#2E303E80",
        "editor.indent_guide_active": "#2E303E",
        "editor.document_highlight.bracket_background": "#E9537817",
        "editor.document_highlight.read_background": "#6C6F9380",
        "editor.document_highlight.write_background": "#6C6F9380",

        "terminal.background": "#00000000",
        "terminal.ansi.background": "#1C1E26",
        "terminal.foreground": "#D5D8DA",
        "terminal.bright_foreground": "#FFFFFF",
        "terminal.dim_foreground": "#D5D8DA80",
        "terminal.ansi.black": "#16161C",
        "terminal.ansi.bright_black": "#232530",
        "terminal.ansi.red": "#E95678",
        "terminal.ansi.bright_red": "#EC6A88",
        "terminal.ansi.green": "#29D398",
        "terminal.ansi.bright_green": "#3FDAA4",
        "terminal.ansi.yellow": "#FAB795",
        "terminal.ansi.bright_yellow": "#FBC3A7",
        "terminal.ansi.blue": "#26BBD9",
        "terminal.ansi.bright_blue": "#3FC4DE",
        "terminal.ansi.magenta": "#EE64AC",
        "terminal.ansi.bright_magenta": "#F075B5",
        "terminal.ansi.cyan": "#59E1E3",
        "terminal.ansi.bright_cyan": "#6BE4E6",
        "terminal.ansi.white": "#D5D8DA",
        "terminal.ansi.bright_white": "#FFFFFF",

        "link_text.hover": "#E95378",
        "search.match_background": "#6C6F9380",
        "search.active_match_background": "#F43E5C4D",

        "conflict": "#FAB795E6",
        "created": "#09F7A0B3",
        "deleted": "#F43E5CB3",
        "modified": "#FAB38EE6",
        "hidden": "#D5D8DA4D",
        "ignored": "#D5D8DA4D",
        "renamed": "#25B0BCE6",

        "players": [
          {
            "cursor": "#E95378",
            "background": "#E95378",
            "selection": "#2E303EB3"
          },
          {
            "cursor": "#25B0BC",
            "background": "#25B0BC",
            "selection": "#25B0BC40"
          },
          {
            "cursor": "#B877DB",
            "background": "#B877DB",
            "selection": "#B877DB40"
          },
          {
            "cursor": "#FAB795",
            "background": "#FAB795",
            "selection": "#FAB79540"
          },
          {
            "cursor": "#09F7A0",
            "background": "#09F7A0",
            "selection": "#09F7A040"
          },
          {
            "cursor": "#26BBD9",
            "background": "#26BBD9",
            "selection": "#26BBD940"
          },
          {
            "cursor": "#EE64AC",
            "background": "#EE64AC",
            "selection": "#EE64AC40"
          },
          {
            "cursor": "#FAC29A",
            "background": "#FAC29A",
            "selection": "#FAC29A40"
          }
        ],

        "syntax": {
          "attribute": { "color": "#F09483E6" },
          "boolean": { "color": "#F09483E6" },
          "comment": { "color": "#BBBBBB4D", "font_style": "italic" },
          "comment.doc": { "color": "#BBBBBB80", "font_style": "italic" },
          "constant": { "color": "#F09483E6" },
          "constructor": { "color": "#FAC29AE6" },
          "embedded": { "color": "#B877DBE6" },
          "emphasis": { "color": "#25B0BCE6", "font_style": "italic" },
          "emphasis.strong": { "color": "#B877DBE6", "font_weight": 700 },
          "enum": { "color": "#FAC29AE6" },
          "function": { "color": "#25B0BCE6" },
          "function.builtin": { "color": "#25B0BCE6" },
          "function.call": { "color": "#25B0BCE6" },
          "function.definition": { "color": "#25B0BCE6" },
          "function.method": { "color": "#25B0BCE6" },
          "function.method.builtin": { "color": "#25B0BCE6" },
          "hint": { "color": "#6C6F93" },
          "keyword": { "color": "#B877DBE6" },
          "label": { "color": "#FAC29AE6" },
          "link_text": { "color": "#FAB795E6" },
          "link_uri": { "color": "#25B0BCE6" },
          "number": { "color": "#F09483E6" },
          "operator": { "color": "#BBBBBB" },
          "predictive": { "color": "#6C6F934D" },
          "preproc": { "color": "#B877DBE6" },
          "primary": { "color": "#D5D8DA" },
          "property": { "color": "#E95678E6" },
          "punctuation": { "color": "#BBBBBB" },
          "punctuation.bracket": { "color": "#E95678B3" },
          "punctuation.delimiter": { "color": "#BBBBBB" },
          "punctuation.list_marker": { "color": "#F09483E6" },
          "punctuation.special": { "color": "#B877DBE6" },
          "string": { "color": "#FAB795E6" },
          "string.escape": { "color": "#25B0BCE6" },
          "string.regex": { "color": "#F09483E6" },
          "string.special": { "color": "#F09483E6" },
          "string.special.symbol": { "color": "#FAB795E6" },
          "tag": { "color": "#E95678E6" },
          "text.literal": { "color": "#F09483E6" },
          "title": { "color": "#E95678E6" },
          "type": { "color": "#FAC29AE6" },
          "type.builtin": { "color": "#FAC29AE6" },
          "variable": { "color": "#E95678E6" },
          "variable.builtin": { "color": "#FAC29AE6", "font_style": "italic" },
          "variable.member": { "color": "#E95678E6" },
          "variable.parameter": {
            "color": "#E95678E6",
            "font_style": "italic"
          },
          "variant": { "color": "#FAC29AE6" }
        }
      }
    },
    {
      "name": "Zedrizon | Horizon Bright",
      "appearance": "light",
      "style": {
        "background": "#FDF0ED",
        "elevated_surface.background": "#FADAD1",
        "surface.background": "#FDF0ED",

        "accents": ["#E84A72"],

        "text": "#06060C",
        "text.muted": "#06060CB3",
        "text.placeholder": "#06060C80",
        "text.disabled": "#06060C4D",
        "text.accent": "#E84A72",

        "icon": "#06060CE6",
        "icon.muted": "#06060CB3",
        "icon.disabled": "#06060C4D",
        "icon.placeholder": "#06060C4D",
        "icon.accent": "#E84A72",

        "border": "#1A1C231A",
        "border.variant": "#FADAD1",
        "border.focused": "#E73665",
        "border.selected": "#E84A72",
        "border.transparent": "#00000000",
        "border.disabled": "#1A1C231A",

        "element.background": "#00000000",
        "element.hover": "#F9CBBE80",
        "element.active": "#F9CBBEB3",
        "element.selected": "#F9CBBE80",
        "element.disabled": "#00000000",
        "error": "#F43E5C",
        "error.background": "#F43E5C1A",
        "warning": "#1EB980",
        "warning.background": "#1EB9801A",
        "success": "#07DA8C",
        "success.background": "#07DA8C1A",
        "info": "#26BBD9",
        "info.background": "#F9CBBE",

        "ghost_element.background": "#00000000",
        "ghost_element.hover": "#F9CBBE80",
        "ghost_element.active": "#F9CBBEB3",
        "ghost_element.selected": "#F9CBBE80",
        "ghost_element.disabled": "#00000000",

        "drop_target.background": "#F9CBBE80",

        "status_bar.background": "#FDF0ED",
        "title_bar.background": "#FDF0ED",
        "title_bar.inactive_background": "#FDF0ED",
        "toolbar.background": "#FDF0ED",
        "tab_bar.background": "#FDF0ED",
        "tab.inactive_background": "#FDF0ED",
        "tab.active_background": "#FDF0ED",
        "panel.background": "#FDF0ED",
        "pane.focused_border": "#E73665",

        "scrollbar.thumb.background": "#F9CEC380",
        "scrollbar.thumb.hover_background": "#F9CEC3B3",
        "scrollbar.thumb.border": "#00000000",
        "scrollbar.track.background": "#00000000",
        "scrollbar.track.border": "#1A1C231A",

        "editor.foreground": "#06060C",
        "editor.background": "#FDF0ED",
        "editor.gutter.background": "#FDF0ED",
        "editor.subheader.background": "#FADAD1",
        "editor.active_line.background": "#F9CBBE4D",
        "editor.highlighted_line.background": "#F9CBBE4D",
        "editor.line_number": "#06060C1A",
        "editor.active_line_number": "#06060C80",
        "editor.invisible": "#06060C1A",
        "editor.wrap_guide": "#F9CEC34D",
        "editor.active_wrap_guide": "#F9CEC34D",
        "editor.indent_guide": "#F9CBBE80",
        "editor.indent_guide_active": "#F9CBBE",
        "editor.document_highlight.read_background": "#F9CEC380",
        "editor.document_highlight.write_background": "#F9CEC380",

        "terminal.background": "#FDF0ED",
        "terminal.foreground": "#06060C",
        "terminal.bright_foreground": "#000000",
        "terminal.dim_foreground": "#06060C80",
        "terminal.ansi.black": "#16161C",
        "terminal.ansi.bright_black": "#FADAD1",
        "terminal.ansi.red": "#E95678",
        "terminal.ansi.bright_red": "#EC6A88",
        "terminal.ansi.green": "#29D398",
        "terminal.ansi.bright_green": "#3FDAA4",
        "terminal.ansi.yellow": "#FAB795",
        "terminal.ansi.bright_yellow": "#FBC3A7",
        "terminal.ansi.blue": "#26BBD9",
        "terminal.ansi.bright_blue": "#3FC4DE",
        "terminal.ansi.magenta": "#EE64AC",
        "terminal.ansi.bright_magenta": "#F075B5",
        "terminal.ansi.cyan": "#59E1E3",
        "terminal.ansi.bright_cyan": "#6BE4E6",
        "terminal.ansi.white": "#D5D8DA",
        "terminal.ansi.bright_white": "#FFFFFF",

        "link_text.hover": "#E84A72",
        "search.match_background": "#F9CEC380",

        "conflict": "#AF5427",
        "created": "#07DA8CB3",
        "deleted": "#F43E5CB3",
        "modified": "#AF5427",
        "hidden": "#06060C4D",
        "ignored": "#06060C4D",
        "renamed": "#1D8991",

        "players": [
          {
            "cursor": "#E84A72",
            "background": "#E84A72",
            "selection": "#F9CBBEB3"
          },
          {
            "cursor": "#1D8991",
            "background": "#1D8991",
            "selection": "#1D899140"
          },
          {
            "cursor": "#8A31B9",
            "background": "#8A31B9",
            "selection": "#8A31B940"
          },
          {
            "cursor": "#F6661E",
            "background": "#F6661E",
            "selection": "#F6661E40"
          },
          {
            "cursor": "#07DA8C",
            "background": "#07DA8C",
            "selection": "#07DA8C40"
          },
          {
            "cursor": "#26BBD9",
            "background": "#26BBD9",
            "selection": "#26BBD940"
          },
          {
            "cursor": "#EE64AC",
            "background": "#EE64AC",
            "selection": "#EE64AC40"
          },
          {
            "cursor": "#F77D26",
            "background": "#F77D26",
            "selection": "#F77D2640"
          }
        ],

        "syntax": {
          "attribute": { "color": "#DC3318" },
          "boolean": { "color": "#DC3318" },
          "comment": { "color": "#33333380", "font_style": "italic" },
          "comment.doc": { "color": "#33333380", "font_style": "italic" },
          "constant": { "color": "#DC3318" },
          "constructor": { "color": "#F77D26" },
          "embedded": { "color": "#8A31B9" },
          "emphasis": { "color": "#1D8991", "font_style": "italic" },
          "emphasis.strong": { "color": "#8A31B9", "font_weight": 700 },
          "enum": { "color": "#F77D26" },
          "function": { "color": "#1D8991" },
          "function.builtin": { "color": "#1D8991" },
          "function.call": { "color": "#1D8991" },
          "function.definition": { "color": "#1D8991" },
          "function.method": { "color": "#1D8991" },
          "function.method.builtin": { "color": "#1D8991" },
          "hint": { "color": "#F9CEC3" },
          "keyword": { "color": "#8A31B9" },
          "label": { "color": "#F77D26" },
          "link_text": { "color": "#F6661E" },
          "link_uri": { "color": "#1D8991" },
          "number": { "color": "#DC3318" },
          "operator": { "color": "#333333" },
          "predictive": { "color": "#F9CEC34D" },
          "preproc": { "color": "#8A31B9" },
          "primary": { "color": "#06060C" },
          "property": { "color": "#DA103F" },
          "punctuation": { "color": "#333333" },
          "punctuation.bracket": { "color": "#DA103FB3" },
          "punctuation.delimiter": { "color": "#333333" },
          "punctuation.list_marker": { "color": "#DC3318" },
          "punctuation.special": { "color": "#8A31B9" },
          "string": { "color": "#F6661E" },
          "string.escape": { "color": "#1D8991" },
          "string.regex": { "color": "#DC3318" },
          "string.special": { "color": "#DC3318" },
          "string.special.symbol": { "color": "#F6661E" },
          "tag": { "color": "#DA103F" },
          "text.literal": { "color": "#DC3318" },
          "title": { "color": "#DA103F" },
          "type": { "color": "#F77D26" },
          "type.builtin": { "color": "#F77D26" },
          "variable": { "color": "#DA103F" },
          "variable.builtin": { "color": "#F77D26", "font_style": "italic" },
          "variable.member": { "color": "#DA103F" },
          "variable.parameter": { "color": "#DA103F", "font_style": "italic" },
          "variant": { "color": "#F77D26" }
        }
      }
    },
    {
      "name": "Zedrizon | Horizon Bright Blur",
      "appearance": "light",
      "style": {
        "background.appearance": "blurred",

        "background": "#FDF0EDD7",
        "elevated_surface.background": "#FADAD1",
        "surface.background": "#FDF0EDD0",

        "accents": ["#E84A72"],

        "text": "#06060C",
        "text.muted": "#06060CB3",
        "text.placeholder": "#06060C80",
        "text.disabled": "#06060C4D",
        "text.accent": "#E84A72",

        "icon": "#06060CE6",
        "icon.muted": "#06060CB3",
        "icon.disabled": "#06060C4D",
        "icon.placeholder": "#06060C4D",
        "icon.accent": "#E84A72",

        "border": "#06060C10",
        "border.variant": "#00000000",
        "border.focused": "#E73665",
        "border.selected": "#E84A72",
        "border.transparent": "#00000000",
        "border.disabled": "#06060C10",

        "element.background": "#00000000",
        "element.hover": "#F9CBBE80",
        "element.active": "#F9CBBEB3",
        "element.selected": "#F9CBBE80",
        "element.disabled": "#00000000",
        "error": "#F43E5C",
        "error.background": "#F43E5C1A",
        "warning": "#1EB980",
        "warning.background": "#1EB9801A",
        "success": "#07DA8C",
        "success.background": "#07DA8C1A",
        "info": "#26BBD9",
        "info.background": "#F9CBBE",

        "ghost_element.background": "#FDF0ED60",
        "ghost_element.hover": "#F9CBBE90",
        "ghost_element.active": "#F9CBBEB3",
        "ghost_element.selected": "#F9CBBE80",
        "ghost_element.disabled": "#00000000",

        "drop_target.background": "#F9CBBE80",

        "status_bar.background": "#FDF0EDD7",
        "title_bar.background": "#FDF0EDD7",
        "title_bar.inactive_background": "#F5E6E2",
        "toolbar.background": "#00000000",
        "tab_bar.background": "#00000000",
        "tab.inactive_background": "#00000000",
        "tab.active_background": "#FADAD1B0",
        "panel.background": "#00000000",
        "panel.focused_border": "#00000000",
        "panel.overlay_background": "#FDF0ED",
        "panel.indent_guide": "#F9CBBE99",
        "panel.indent_guide_active": "#F9CEC3",
        "panel.indent_guide_hover": "#E84A72",
        "pane.focused_border": "#E73665",
        "pane_group.border": "#06060C15",

        "scrollbar.thumb.background": "#F9CEC380",
        "scrollbar.thumb.hover_background": "#F9CEC3B3",
        "scrollbar.thumb.active_background": null,
        "scrollbar.thumb.border": null,
        "scrollbar.track.background": "#00000000",
        "scrollbar.track.border": "#00000000",

        "minimap.thumb.background": "#E84A7233",
        "minimap.thumb.hover_background": "#E84A7266",
        "minimap.thumb.active_background": "#E84A7299",
        "minimap.thumb.border": null,

        "editor.foreground": "#06060C",
        "editor.background": "#00000000",
        "editor.gutter.background": "#00000000",
        "editor.subheader.background": "#FADAD1",
        "editor.active_line.background": "#00000000",
        "editor.highlighted_line.background": "#F9CBBE26",
        "editor.line_number": "#06060C1A",
        "editor.active_line_number": "#06060C80",
        "editor.invisible": "#06060C1A",
        "editor.wrap_guide": "#F9CEC34D",
        "editor.active_wrap_guide": "#F9CEC34D",
        "editor.indent_guide": "#F9CBBE80",
        "editor.indent_guide_active": "#F9CBBE",
        "editor.document_highlight.bracket_background": "#E84A7217",
        "editor.document_highlight.read_background": "#F9CEC380",
        "editor.document_highlight.write_background": "#F9CEC380",

        "terminal.background": "#00000000",
        "terminal.ansi.background": "#FDF0ED",
        "terminal.foreground": "#06060C",
        "terminal.bright_foreground": "#000000",
        "terminal.dim_foreground": "#06060C80",
        "terminal.ansi.black": "#16161C",
        "terminal.ansi.bright_black": "#FADAD1",
        "terminal.ansi.red": "#E95678",
        "terminal.ansi.bright_red": "#EC6A88",
        "terminal.ansi.green": "#29D398",
        "terminal.ansi.bright_green": "#3FDAA4",
        "terminal.ansi.yellow": "#FAB795",
        "terminal.ansi.bright_yellow": "#FBC3A7",
        "terminal.ansi.blue": "#26BBD9",
        "terminal.ansi.bright_blue": "#3FC4DE",
        "terminal.ansi.magenta": "#EE64AC",
        "terminal.ansi.bright_magenta": "#F075B5",
        "terminal.ansi.cyan": "#59E1E3",
        "terminal.ansi.bright_cyan": "#6BE4E6",
        "terminal.ansi.white": "#D5D8DA",
        "terminal.ansi.bright_white": "#FFFFFF",

        "link_text.hover": "#E84A72",
        "search.match_background": "#F9CEC380",
        "search.active_match_background": "#F43E5C4D",

        "conflict": "#AF5427",
        "created": "#07DA8CB3",
        "deleted": "#F43E5CB3",
        "modified": "#AF5427",
        "hidden": "#06060C4D",
        "ignored": "#06060C4D",
        "renamed": "#1D8991",

        "players": [
          {
            "cursor": "#E84A72",
            "background": "#E84A72",
            "selection": "#F9CBBEB3"
          },
          {
            "cursor": "#1D8991",
            "background": "#1D8991",
            "selection": "#1D899140"
          },
          {
            "cursor": "#8A31B9",
            "background": "#8A31B9",
            "selection": "#8A31B940"
          },
          {
            "cursor": "#F6661E",
            "background": "#F6661E",
            "selection": "#F6661E40"
          },
          {
            "cursor": "#07DA8C",
            "background": "#07DA8C",
            "selection": "#07DA8C40"
          },
          {
            "cursor": "#26BBD9",
            "background": "#26BBD9",
            "selection": "#26BBD940"
          },
          {
            "cursor": "#EE64AC",
            "background": "#EE64AC",
            "selection": "#EE64AC40"
          },
          {
            "cursor": "#F77D26",
            "background": "#F77D26",
            "selection": "#F77D2640"
          }
        ],

        "syntax": {
          "attribute": { "color": "#DC3318" },
          "boolean": { "color": "#DC3318" },
          "comment": { "color": "#33333380", "font_style": "italic" },
          "comment.doc": { "color": "#33333380", "font_style": "italic" },
          "constant": { "color": "#DC3318" },
          "constructor": { "color": "#F77D26" },
          "embedded": { "color": "#8A31B9" },
          "emphasis": { "color": "#1D8991", "font_style": "italic" },
          "emphasis.strong": { "color": "#8A31B9", "font_weight": 700 },
          "enum": { "color": "#F77D26" },
          "function": { "color": "#1D8991" },
          "function.builtin": { "color": "#1D8991" },
          "function.call": { "color": "#1D8991" },
          "function.definition": { "color": "#1D8991" },
          "function.method": { "color": "#1D8991" },
          "function.method.builtin": { "color": "#1D8991" },
          "hint": { "color": "#F9CEC3" },
          "keyword": { "color": "#8A31B9" },
          "label": { "color": "#F77D26" },
          "link_text": { "color": "#F6661E" },
          "link_uri": { "color": "#1D8991" },
          "number": { "color": "#DC3318" },
          "operator": { "color": "#333333" },
          "predictive": { "color": "#F9CEC34D" },
          "preproc": { "color": "#8A31B9" },
          "primary": { "color": "#06060C" },
          "property": { "color": "#DA103F" },
          "punctuation": { "color": "#333333" },
          "punctuation.bracket": { "color": "#DA103FB3" },
          "punctuation.delimiter": { "color": "#333333" },
          "punctuation.list_marker": { "color": "#DC3318" },
          "punctuation.special": { "color": "#8A31B9" },
          "string": { "color": "#F6661E" },
          "string.escape": { "color": "#1D8991" },
          "string.regex": { "color": "#DC3318" },
          "string.special": { "color": "#DC3318" },
          "string.special.symbol": { "color": "#F6661E" },
          "tag": { "color": "#DA103F" },
          "text.literal": { "color": "#DC3318" },
          "title": { "color": "#DA103F" },
          "type": { "color": "#F77D26" },
          "type.builtin": { "color": "#F77D26" },
          "variable": { "color": "#DA103F" },
          "variable.builtin": { "color": "#F77D26", "font_style": "italic" },
          "variable.member": { "color": "#DA103F" },
          "variable.parameter": { "color": "#DA103F", "font_style": "italic" },
          "variant": { "color": "#F77D26" }
        }
      }
    }
  ]
}
